df_and_order/__init__.py
df_and_order/common.py
df_and_order/df_cache.py
df_and_order/df_config.py
df_and_order/df_reader.py
df_and_order/df_transform.py
df_and_order/df_transform_state.py
df_and_order/df_transform_step.py
df_and_order/helpers.py
df_and_order/steps/pd.py
df_and_order-0.2.5.dist-info/LICENSE
df_and_order-0.2.5.dist-info/METADATA
df_and_order-0.2.5.dist-info/WHEEL
df_and_order-0.2.5.dist-info/top_level.txt
df_and_order-0.2.5.dist-info/RECORD
