Metadata-Version: 2.1
Name: df-and-order
Version: 0.2.5
Summary: Using df-and-order your interactions with dataframes become very clean and predictable.
Home-page: https://github.com/ityutin/df-and-order
Author: Ilya Tyutin
Author-email: emmarrgghh@gmail.com
License: MIT
Platform: UNKNOWN
Classifier: License :: OSI Approved :: MIT License
Classifier: Programming Language :: Python :: 3
Classifier: Programming Language :: Python :: 3.7
